minidynamicrender/Core.py
minidynamicrender/DynAdditional.py
minidynamicrender/DynConfig.py
minidynamicrender/DynForward.py
minidynamicrender/DynHeader.py
minidynamicrender/DynMajor.py
minidynamicrender/DynText.py
minidynamicrender/Tools.py
minidynamicrender/__init__.py
minidynamicrender-1.2.6.dist-info/LICENSE
minidynamicrender-1.2.6.dist-info/WHEEL
minidynamicrender-1.2.6.dist-info/METADATA
minidynamicrender-1.2.6.dist-info/RECORD
