Metadata-Version: 2.1
Name: minidynamicrender
Version: 1.2.6
Summary: A package that transform bilibili's dynamic data to image
Author: DMC
Author-email: lzxder@outlook.com
Requires-Python: >=3.8,<4.0
Classifier: Programming Language :: Python :: 3
Classifier: Programming Language :: Python :: 3.8
Classifier: Programming Language :: Python :: 3.9
Classifier: Programming Language :: Python :: 3.10
Classifier: Programming Language :: Python :: 3.11
Requires-Dist: dynamicadaptor (>=0.4.3,<0.5.0)
Requires-Dist: emoji (>=2.2.0,<3.0.0)
Requires-Dist: fonttools (>=4.38.0,<5.0.0)
Requires-Dist: httpx (>=0.24.0,<0.25.0)
Requires-Dist: loguru (>=0.6.0,<0.7.0)
Requires-Dist: numpy (>=1.24.1,<2.0.0)
Requires-Dist: pillow (>=9.4.0,<10.0.0)
Requires-Dist: qrcode (>=7.3.1,<8.0.0)
